opengeodeweb_viewer/__init__.py
opengeodeweb_viewer/config.py
opengeodeweb_viewer/py.typed
opengeodeweb_viewer/utils_functions.py
opengeodeweb_viewer/vtk_protocol.py
opengeodeweb_viewer/vtkw_server.py
opengeodeweb_viewer/object/object_methods.py
opengeodeweb_viewer/rpc/utils_protocols.py
opengeodeweb_viewer/rpc/generic/generic_protocols.py
opengeodeweb_viewer/rpc/generic/schemas/__init__.py
opengeodeweb_viewer/rpc/generic/schemas/deregister.json
opengeodeweb_viewer/rpc/generic/schemas/deregister.py
opengeodeweb_viewer/rpc/generic/schemas/register.json
opengeodeweb_viewer/rpc/generic/schemas/register.py
opengeodeweb_viewer/rpc/mesh/mesh_protocols.py
opengeodeweb_viewer/rpc/mesh/cells/cells_protocols.py
opengeodeweb_viewer/rpc/mesh/cells/schemas/__init__.py
opengeodeweb_viewer/rpc/mesh/cells/schemas/cell_attribute.json
opengeodeweb_viewer/rpc/mesh/cells/schemas/cell_attribute.py
opengeodeweb_viewer/rpc/mesh/cells/schemas/cell_color_map.json
opengeodeweb_viewer/rpc/mesh/cells/schemas/cell_color_map.py
opengeodeweb_viewer/rpc/mesh/cells/schemas/cell_scalar_range.json
opengeodeweb_viewer/rpc/mesh/cells/schemas/cell_scalar_range.py
opengeodeweb_viewer/rpc/mesh/cells/schemas/color.json
opengeodeweb_viewer/rpc/mesh/cells/schemas/color.py
opengeodeweb_viewer/rpc/mesh/cells/schemas/vertex_attribute.json
opengeodeweb_viewer/rpc/mesh/cells/schemas/vertex_attribute.py
opengeodeweb_viewer/rpc/mesh/cells/schemas/vertex_color_map.json
opengeodeweb_viewer/rpc/mesh/cells/schemas/vertex_color_map.py
opengeodeweb_viewer/rpc/mesh/cells/schemas/vertex_scalar_range.json
opengeodeweb_viewer/rpc/mesh/cells/schemas/vertex_scalar_range.py
opengeodeweb_viewer/rpc/mesh/cells/schemas/visibility.json
opengeodeweb_viewer/rpc/mesh/cells/schemas/visibility.py
opengeodeweb_viewer/rpc/mesh/edges/mesh_edges_protocols.py
opengeodeweb_viewer/rpc/mesh/edges/schemas/__init__.py
opengeodeweb_viewer/rpc/mesh/edges/schemas/color.json
opengeodeweb_viewer/rpc/mesh/edges/schemas/color.py
opengeodeweb_viewer-1.14.0.dist-info/licenses/LICENSE
opengeodeweb_viewer-1.14.0.dist-info/METADATA
opengeodeweb_viewer-1.14.0.dist-info/WHEEL
opengeodeweb_viewer-1.14.0.dist-info/entry_points.txt
opengeodeweb_viewer-1.14.0.dist-info/top_level.txt
opengeodeweb_viewer-1.14.0.dist-info/RECORD
