Metadata-Version: 2.4
Name: OpenGeodeWeb-Viewer
Version: 1.14.0
Summary: OpenGeodeWeb-Viewer is an open source framework that proposes handy python functions and wrappers for the OpenGeode ecosystem
Author-email: Geode-solutions <team-web@geode-solutions.com>
Project-URL: Homepage, https://github.com/Geode-solutions/OpenGeodeWeb-Viewer
Project-URL: Bug Tracker, https://github.com/Geode-solutions/OpenGeodeWeb-Viewer/issues
Classifier: Programming Language :: Python :: 3
Classifier: License :: OSI Approved :: MIT License
Classifier: Operating System :: OS Independent
Requires-Python: >=3.9
License-File: LICENSE
Requires-Dist: aiohappyeyeballs>=2
Requires-Dist: aiohttp>=3
Requires-Dist: aiosignal>=1
Requires-Dist: attrs>=25
Requires-Dist: contourpy>=1
Requires-Dist: cycler>=0
Requires-Dist: fonttools>=4
Requires-Dist: frozenlist>=1
Requires-Dist: idna==3.11
Requires-Dist: kiwisolver>=1
Requires-Dist: matplotlib>=3
Requires-Dist: multidict>=6
Requires-Dist: numpy>=2
Requires-Dist: packaging==25.0
Requires-Dist: pillow>=12
Requires-Dist: propcache>=0
Requires-Dist: pyparsing>=3
Requires-Dist: python-dateutil==2.9.0.post0
Requires-Dist: six>=1
Requires-Dist: typing-extensions>=4
Requires-Dist: vtk==9.5.2
Requires-Dist: websocket-client>=1
Requires-Dist: wslink==1.12.4
Requires-Dist: yarl>=1
Requires-Dist: opengeodeweb-microservice==1.*,>=1.0.12
Dynamic: license-file
